{
  "id": "019d2bf7-fc43-770a-a4c1-20a9a45b3bec",
  "code": "1.012525",
  "name": "Sửa đổi, bổ sung thông tin của doanh nghiệp đã được cấp Mã số tân trang theo Hiệp định EVFTA và Hiệp định UKVFTA",
  "detail": {
    "id": "019d2bf7-fc43-770a-a4c1-20a9a45b3bec",
    "code": "1.012525",
    "codeNotation": "1.012525",
    "executionSteps": [
      {
        "name": "",
        "description": "Trình tự thực hiện\nBước 1: Doanh nghiệp tân trang hoặc chủ sở hữu nhãn hiệu (sau đây gọi là doanh nghiệp đề nghị) gửi 01 bộ hồ sơ đề nghị tới Bộ Công Thương. \nBước 2: Bộ Công Thương kiểm tra tính hợp lệ, đầy đủ của hồ sơ. \n- Trường hợp hồ sơ đề nghị sửa đổi, bổ sung thông tin có liên quan tới Phụ lục từ I đến VII Nghị định số 66/2024/NĐ-CP:\nBước 3: Trong thời hạn 07 ngày kể từ ngày nhận được hồ sơ đúng quy định, Bộ Công Thương gửi hồ sơ để lấy ý kiến bộ quản lý chuyên ngành.\nBước 4: Trong thời hạn 10 ngày kể từ ngày nhận được hồ sơ từ Bộ Công Thương, bộ quản lý chuyên ngành có văn bản trả lời Bộ Công Thương.\nBước 5: Nếu bộ quản lý chuyên ngành kết luận việc sửa đổi, bổ sung thông tin không gây ảnh hưởng tới năng lực tân trang, chế độ bảo hành, bảo dưỡng, xuất xứ hàng hóa và quyền sử dụng nhãn hiệu, trong thời hạn 7 ngày kể từ ngày nhận được văn bản trả lời của bộ quản lý chuyên ngành, Bộ Công Thương ra thông báo bằng văn bản chấp thuận đề nghị sửa đổi, bổ sung thông tin. \nTrường hợp Bộ Công Thương hoặc bộ quản lý chuyên ngành nhận thấy việc sửa đổi, bổ sung thông tin có khả năng gây ảnh hưởng tới năng lực tân trang, chế độ bảo hành, bảo dưỡng, xuất xứ hàng hóa và quyền sử dụng nhãn hiệu của doanh nghiệp đã được cấp Mã số tân trang, trong thời hạn 10 ngày kể từ ngày nhận được văn bản trả lời của bộ quản lý chuyên ngành, Bộ Công Thương thông báo bằng văn bản cho doanh nghiệp đã được cấp Mã số tân trang về việc thẩm định lại năng lực. \n- Trường hợp hồ sơ đề nghị sửa đổi, bổ sung thông tin chỉ liên quan tới Phụ lục IV Nghị định số 66/2024/NĐ-CP:\nBước 3: Trường hợp Bộ Công Thương nhận thấy việc sửa đổi, bổ sung thông tin không gây ảnh hưởng tới năng lực tân trang, chế độ bảo hành, bảo dưỡng, xuất xứ hàng hóa và quyền sử dụng nhãn hiệu, trong thời hạn 10 ngày kể từ ngày nhận được hồ sơ đúng quy định, Bộ Công Thương ra thông báo bằng văn bản chấp thuận đề nghị sửa đổi, bổ sung thông tin.\nTrường hợp Bộ Công Thương nhận thấy việc sửa đổi, bổ sung thông tin có khả năng gây ảnh hưởng tới năng lực tân trang, chế độ bảo hành, bảo dưỡng, xuất xứ hàng hóa và quyền sử dụng nhãn hiệu của doanh nghiệp đã được cấp Mã số tân trang, trong thời hạn 10 ngày kể từ ngày nhận được hồ sơ đúng quy định, Bộ Công Thương thông báo bằng văn bản cho doanh nghiệp đã được cấp Mã số tân trang về việc thẩm định lại năng lực.\n"
      }
    ],
    "executionMethods": [
      {
        "submissionMethod": "ONLINE",
        "processingTime": 10,
        "processingTimeUnit": "DAY",
        "description": "",
        "fees": [
          {
            "type": "FEE",
            "value": 0,
            "currencyId": "",
            "attachment": null,
            "description": ""
          }
        ]
      },
      {
        "submissionMethod": "POSTAL",
        "processingTime": 10,
        "processingTimeUnit": "DAY",
        "description": "",
        "fees": [
          {
            "type": "FEE",
            "value": 0,
            "currencyId": "",
            "attachment": null,
            "description": ""
          }
        ]
      },
      {
        "submissionMethod": "DIRECT",
        "processingTime": 10,
        "processingTimeUnit": "DAY",
        "description": "",
        "fees": [
          {
            "type": "FEE",
            "value": 0,
            "currencyId": "",
            "attachment": null,
            "description": ""
          }
        ]
      }
    ],
    "description": "",
    "name": "Sửa đổi, bổ sung thông tin của doanh nghiệp đã được cấp Mã số tân trang theo Hiệp định EVFTA và Hiệp định UKVFTA",
    "decisionNo": "",
    "executionCases": [
      {
        "name": "",
        "profileComponents": [
          {
            "profileComponentId": "019d2bb8-7174-7359-aac6-df854481dbc9",
            "originalQty": 1,
            "copyQty": 0,
            "required": false,
            "hasElectronicForm": false,
            "isProcessingResult": false,
            "name": "+ Tài liệu thuyết minh đề nghị sửa đổi, bổ sung thông tin (01 bản chính bằng tiếng Anh và 01 bản dịch tiếng Việt, cả 2 bản được ký bởi đại diện có thẩm quyền của doanh nghiệp)",
            "code": "000.00.00.G02-KQ004814",
            "attachments": []
          },
          {
            "profileComponentId": "019d2bb8-7174-7359-aac6-d8f875c54cb9",
            "originalQty": 1,
            "copyQty": 0,
            "required": false,
            "hasElectronicForm": false,
            "isProcessingResult": false,
            "name": "+ Đơn đề nghị sửa đổi, bổ sung thông tin theo mẫu tại Phụ lục XI ban hành kèm theo Nghị định số 66/2024/NĐ-CP (01 bản chính)",
            "code": "000.00.00.G02-KQ004813",
            "attachments": [
              {
                "id": "019d8b62-9bee-7078-950e-67657899f9ee",
                "fileName": "PHỤ LỤC XI.docx",
                "bucketName": "dvc",
                "filePath": "configuring/019d8b62-9bee-7078-950e-67657899f9ee/PHỤ LỤC XI.docx"
              }
            ]
          },
          {
            "profileComponentId": "019d2bb8-7174-7359-aac6-e366b87bfe4f",
            "originalQty": 1,
            "copyQty": 0,
            "required": false,
            "hasElectronicForm": false,
            "isProcessingResult": false,
            "name": "+ Bản sao các tài liệu hỗ trợ cho tài liệu thuyết minh, nếu có (mỗi tài liệu 01 bản sao kèm theo bản dịch tiếng Việt, cả 2 bản được xác thực bởi đại diện có thẩm quyền của doanh nghiệp)",
            "code": "000.00.00.G02-KQ004815",
            "attachments": []
          }
        ]
      }
    ],
    "formalityTargetType": [],
    "formalityType": "ASSIGNED_REGULATION",
    "state": "ACTIVE",
    "isInternal": false,
    "type": "STANDARD",
    "isWard": false,
    "isProvince": false,
    "isMinistry": true,
    "isOtherAgency": false,
    "isUndetermined": false,
    "isVertical": false,
    "isFullProcess": false,
    "isSharedService": false,
    "note": "",
    "keywords": "",
    "categoryIds": [
      "019d2bbb-69ee-7079-a6b1-21d46fc1c3f8"
    ],
    "serviceGroupIds": [],
    "legalBasisIds": [
      "019d2bb3-5d7f-719e-b470-3e41eed921c7",
      "019d2bb3-5d7f-719e-b46c-7fe9c28ad813",
      "019d2bb3-5d84-71c5-b671-79b7220b4ed0",
      "019d2bb3-5d84-71c5-b671-3e47e4d388c3"
    ],
    "resultIds": [
      "019d2bb2-1c39-7291-ba48-624eebc23d28"
    ],
    "subjectTypeIds": [
      "019b698b-07d7-7768-b827-9fcf3b2cbfec"
    ],
    "departmentExecutingIds": [
      "019d2be3-6a80-747a-9d08-743a99576062"
    ],
    "departmentAuthorityIds": [],
    "departmentAuthorizedIds": [],
    "departmentCoordinatingIds": [],
    "categoriesDetails": [
      {
        "id": "019d2bbb-69ee-7079-a6b1-21d46fc1c3f8",
        "name": "Xuất nhập khẩu",
        "code": "G02-CT22"
      }
    ],
    "departmentDetails": [],
    "departmentsExecuting": [
      {
        "id": "019d2be3-6a80-747a-9d08-743a99576062",
        "name": "Cục Xuất nhập khẩu",
        "code": "G02.23"
      }
    ],
    "departmentsAuthority": [],
    "departmentsAuthorized": [],
    "departmentsCoordinating": [],
    "unitGroupExecutingIds": [],
    "unitGroupAuthorityIds": [],
    "unitGroupAuthorizedIds": [],
    "unitGroupCoordinatingIds": [],
    "unitGroupsExecuting": [],
    "unitGroupsAuthority": [],
    "unitGroupsAuthorized": [],
    "unitGroupsCoordinating": [],
    "serviceGroupsDetails": [],
    "legalBasisesDetails": [
      {
        "id": "019d2bb3-5d7f-719e-b470-3e41eed921c7",
        "name": "Nghị định số 66/2024/NĐ-CP",
        "code": "66/2024/NĐ-CP"
      },
      {
        "id": "019d2bb3-5d7f-719e-b46c-7fe9c28ad813",
        "name": "Nghị quyết 31/NQ-CP phê duyệt Hiệp định thương mại giữa Việt Nam và liên hiệp Vương quốc Anh",
        "code": "31/NQ-CP"
      },
      {
        "id": "019d2bb3-5d84-71c5-b671-3e47e4d388c3",
        "name": "Luật quản lý ngoại thương",
        "code": "05/2017/QH14"
      },
      {
        "id": "019d2bb3-5d84-71c5-b671-79b7220b4ed0",
        "name": "Nghị quyết số 102/2020/QH14",
        "code": "102/2020/QH14"
      }
    ],
    "resultsDetails": [
      {
        "id": "019d2bb2-1c39-7291-ba48-624eebc23d28",
        "name": "Văn bản chấp thuận đề nghị sửa đổi, bổ sung thông tin về Mã số tân trang.",
        "code": "KQ.G02.000306"
      }
    ],
    "subjectTypesDetails": [
      {
        "id": "019b698b-07d7-7768-b827-9fcf3b2cbfec",
        "name": "Doanh nghiệp",
        "code": "ĐT2"
      }
    ],
    "departmentPromulgateId": "019d2be3-6a72-700f-a652-b16ccb65a5c0",
    "departmentPromulgateCode": "G02",
    "departmentPromulgateName": "Bộ Công thương",
    "cases": [
      {
        "id": "019d2cb3-5b97-701b-99e6-0b39afef7871",
        "name": "Sửa đổi, bổ sung thông tin của doanh nghiệp đã được cấp Mã số tân trang theo Hiệp định EVFTA và Hiệp định UKVFTA",
        "code": "1.012525.01",
        "processingDay": {
          "qty": 10,
          "type": "DAY"
        },
        "profileComponents": []
      }
    ],
    "fees": [],
    "createdAt": 1776322247656,
    "updatedAt": 1776322247656,
    "profileComponents": [],
    "targetObjects": [],
    "executingAgencies": "Cục Xuất nhập khẩu",
    "authorizedAgencies": "",
    "dossierReceivingAddresses": "",
    "delegatedAgencies": "",
    "coordinatingAgencies": "",
    "requirementsAndConditions": "",
    "procedureRelatedGroup": [],
    "procedureProposal": {
      "id": "019d2cb3-19bc-7520-9b12-aa49a600939c",
      "proposalNumber": "1625/QĐ-BCT",
      "decisionDate": 1718841600000,
      "decisionNumber": null,
      "publicationDate": 1776322247431,
      "issuingAgency": {
        "id": "019d2be3-6a72-700f-a652-b16ccb65a5c0",
        "name": "Bộ Công thương"
      },
      "proposalType": "STANDARD"
    },
    "isOfflineOnly": false,
    "isNonTerritorial": false,
    "returningMethods": []
  }
}