{
  "id": "019d2bfd-5730-745b-8f0b-7d02a8ce43cd",
  "code": "1.002181",
  "name": "Đăng ký hoạt động của chi nhánh, công ty luật nước ngoài",
  "detail": {
    "id": "019d2bfd-5730-745b-8f0b-7d02a8ce43cd",
    "code": "1.002181",
    "codeNotation": "1.002181",
    "executionSteps": [
      {
        "name": "",
        "description": "Trong thời hạn 60 ngày, kể từ ngày được cấp Giấy phép thành lập, chi nhánh, công ty luật nước ngoài phải đăng ký hoạt động tại Sở Tư pháp ở địa phương nơi đặt trụ sở.\nTrong thời hạn 07 ngày làm việc, kể từ ngày nhận đủ hồ sơ, Sở Tư pháp cấp Giấy đăng ký hoạt động cho chi nhánh, công ty luật nước ngoài."
      }
    ],
    "executionMethods": [
      {
        "submissionMethod": "ONLINE",
        "processingTime": 7,
        "processingTimeUnit": "WORKING_DAY",
        "description": "",
        "fees": [
          {
            "type": "FEE",
            "value": 2000000,
            "currencyId": "019b3fb2-b5b8-70ac-85e2-9409ec1eaffa",
            "attachment": null,
            "description": "(áp dụng mức phí 1.000.000 đồng/hồ sơ kể từ ngày 01/7/2025 đến hết ngày 31/12/2026 theo Thông tư số 64/2025/TT-BTC)",
            "currencyName": "Việt Nam Đồng"
          }
        ]
      },
      {
        "submissionMethod": "POSTAL",
        "processingTime": 7,
        "processingTimeUnit": "WORKING_DAY",
        "description": "",
        "fees": [
          {
            "type": "FEE",
            "value": 2000000,
            "currencyId": "019b3fb2-b5b8-70ac-85e2-9409ec1eaffa",
            "attachment": null,
            "description": "(áp dụng mức phí 1.000.000 đồng/hồ sơ kể từ ngày 01/7/2025 đến hết ngày 31/12/2026 theo Thông tư số 64/2025/TT-BTC)",
            "currencyName": "Việt Nam Đồng"
          }
        ]
      },
      {
        "submissionMethod": "DIRECT",
        "processingTime": 7,
        "processingTimeUnit": "WORKING_DAY",
        "description": "",
        "fees": [
          {
            "type": "FEE",
            "value": 2000000,
            "currencyId": "019b3fb2-b5b8-70ac-85e2-9409ec1eaffa",
            "attachment": null,
            "description": "(áp dụng mức phí 1.000.000 đồng/hồ sơ kể từ ngày 01/7/2025 đến hết ngày 31/12/2026 theo Thông tư số 64/2025/TT-BTC)",
            "currencyName": "Việt Nam Đồng"
          }
        ]
      }
    ],
    "description": "",
    "name": "Đăng ký hoạt động của chi nhánh, công ty luật nước ngoài",
    "decisionNo": "",
    "executionCases": [
      {
        "name": "",
        "profileComponents": [
          {
            "profileComponentId": "019d2bb8-71b8-7770-8075-d00bc02101af",
            "originalQty": 0,
            "copyQty": 1,
            "required": false,
            "hasElectronicForm": false,
            "isProcessingResult": false,
            "name": "Giấy tờ chứng minh về trụ sở",
            "code": "000.00.00.G15-KQ1043",
            "attachments": []
          }
        ]
      }
    ],
    "formalityTargetType": [],
    "formalityType": "ASSIGNED_REGULATION",
    "state": "UPDATED",
    "isInternal": false,
    "type": "STANDARD",
    "isWard": false,
    "isProvince": true,
    "isMinistry": false,
    "isOtherAgency": false,
    "isUndetermined": false,
    "isVertical": false,
    "isFullProcess": true,
    "isSharedService": false,
    "note": "",
    "keywords": "",
    "categoryIds": [
      "019d2bbb-69ee-7079-a6b4-5b383dd0cc28"
    ],
    "serviceGroupIds": [],
    "legalBasisIds": [
      "019d2bb3-5d7d-7398-be48-16487abac133",
      "019d2bb3-5d7d-7398-be4e-69cce97f8824",
      "019d2bb3-5d84-71c5-b672-05ecd30521ff",
      "019d2bb3-5d84-71c5-b673-e35e393d0c28",
      "019df0a7-9b83-75ea-abf3-9982f285a420"
    ],
    "resultIds": [
      "019d2bb2-1c78-7725-a750-51fcaac2e4ef",
      "019d2bb2-1c78-7725-a750-55838a11c3ec",
      "019d2bb2-1c78-7725-a750-b05ccc3f80bb",
      "019d2bb2-1c78-7725-a750-baa18b7b6641"
    ],
    "subjectTypeIds": [
      "019b698e-91f0-7769-93ad-b9a2b156f5f7"
    ],
    "departmentExecutingIds": [
      "019d2be3-6a81-771b-b67e-96bf5cac1e39"
    ],
    "departmentAuthorityIds": [],
    "departmentAuthorizedIds": [],
    "departmentCoordinatingIds": [],
    "categoriesDetails": [
      {
        "id": "019d2bbb-69ee-7079-a6b4-5b383dd0cc28",
        "name": "Luật sư",
        "code": "G15-TP09"
      }
    ],
    "category": {
      "id": "019d2bbb-69ee-7079-a6b4-5b383dd0cc28",
      "name": "Luật sư",
      "code": "G15-TP09"
    },
    "departmentDetails": [],
    "departmentsExecuting": [
      {
        "id": "019d2be3-6a81-771b-b67e-96bf5cac1e39",
        "name": "Sở Tư pháp",
        "code": "000.00.CS.002"
      }
    ],
    "departmentsAuthority": [],
    "departmentsAuthorized": [],
    "departmentsCoordinating": [],
    "unitGroupExecutingIds": [],
    "unitGroupAuthorityIds": [],
    "unitGroupAuthorizedIds": [],
    "unitGroupCoordinatingIds": [],
    "unitGroupsExecuting": [],
    "unitGroupsAuthority": [],
    "unitGroupsAuthorized": [],
    "unitGroupsCoordinating": [],
    "serviceGroupsDetails": [],
    "legalBasisesDetails": [
      {
        "id": "019d2bb3-5d7d-7398-be48-16487abac133",
        "name": "Thông tư số 220/2016/TT-BTC của Bộ trưởng Bộ Tài chính ngày 10/11/2016 quy định mức thu, chế độ thu, nộp, quản lý phí, lệ phí trong lĩnh vực hoạt động luật sư",
        "code": "220/2016/TT-BTC"
      },
      {
        "id": "019d2bb3-5d84-71c5-b673-e35e393d0c28",
        "name": "Luật 65/2006/QH11",
        "code": "65/2006/QH11"
      },
      {
        "id": "019d2bb3-5d7d-7398-be4e-69cce97f8824",
        "name": "Thông tư quy định mức thu, miễn một số khoản phí, lệ phí nhằm hỗ trợ cho doanh nghiệp, người dân",
        "code": "64/2025/TT-BTC"
      },
      {
        "id": "019d2bb3-5d84-71c5-b672-05ecd30521ff",
        "name": "Luật 20/2012/QH13",
        "code": "20/2012/QH13"
      },
      {
        "id": "019df0a7-9b83-75ea-abf3-9982f285a420",
        "name": "Nghị quyết của Chính phủ quy định cắt giảm, đơn giản hóa thủ tục hành chính, quy định liên quan đến hoạt động sản xuất, kinh doanh",
        "code": "66.16/2026/NQ-CP "
      }
    ],
    "resultsDetails": [
      {
        "id": "019d2bb2-1c78-7725-a750-55838a11c3ec",
        "name": "Giấy đăng ký hoạt động của công ty luật trách nhiệm hữu hạn hai thành viên trở lên, công ty luật hợp danh",
        "code": "000.00.00.G15-KQ0187"
      },
      {
        "id": "019d2bb2-1c78-7725-a750-b05ccc3f80bb",
        "name": "Giấy ĐKHĐ của Công ty Luật TNHH 100% vốn nước ngoài tại Việt Nam",
        "code": "KQ.G15.000118"
      },
      {
        "id": "019d2bb2-1c78-7725-a750-51fcaac2e4ef",
        "name": "Giấy ĐKHĐ Công ty Luật TNHH dưới hình thức liên doanh tại Việt Nam",
        "code": "KQ.G15.000091"
      },
      {
        "id": "019d2bb2-1c78-7725-a750-baa18b7b6641",
        "name": "Giấy ĐKHĐ Chi nhánh của tổ chức hành nghề luật sư nước ngoài tại Việt Nam",
        "code": "KQ.G15.000120"
      }
    ],
    "subjectTypesDetails": [
      {
        "id": "019b698e-91f0-7769-93ad-b9a2b156f5f7",
        "name": "Tổ chức (không bao gồm doanh nghiệp, HTX)",
        "code": "ĐT9"
      }
    ],
    "departmentPromulgateId": "019d2be3-6a72-700f-a652-d603f1537007",
    "departmentPromulgateCode": "G15",
    "departmentPromulgateName": "Bộ Tư pháp",
    "cases": [
      {
        "id": "019d2dd9-cec8-71aa-9660-a2fa9cda0435",
        "name": "Đăng ký hoạt động của chi nhánh, công ty luật nước ngoài",
        "code": "1.002181.01",
        "processingDay": {
          "qty": 10,
          "type": "WORKING_DAY"
        },
        "profileComponents": []
      }
    ],
    "fees": [],
    "createdAt": 1774559516464,
    "updatedAt": 1779025085309,
    "profileComponents": [],
    "targetObjects": [],
    "executingAgencies": "Sở Tư pháp",
    "authorizedAgencies": "",
    "dossierReceivingAddresses": "",
    "delegatedAgencies": "",
    "coordinatingAgencies": "",
    "requirementsAndConditions": "",
    "procedureRelatedGroup": [],
    "procedureProposal": {
      "id": "019e2b08-d099-73bc-972a-714721712b87",
      "proposalNumber": "1262/QĐ-BTP",
      "decisionDate": 1778691600000,
      "decisionNumber": null,
      "publicationDate": 1779025314210,
      "issuingAgency": {
        "id": "019d2be3-6a72-700f-a652-d603f1537007",
        "name": "Bộ Tư pháp"
      },
      "proposalType": "STANDARD"
    },
    "isOfflineOnly": false,
    "isNonTerritorial": false,
    "returningMethods": []
  }
}