{
  "schema_version": "3.0-pdf",
  "record_type": "public_service_procedure_knowledge",
  "id": "019d2bf9-ab35-74bd-9458-f64db6c73bdb",
  "procedure_code": "2.002794",
  "title": "Cấp giấy chứng nhận doanh nghiệp thành lập mới từ dự án đầu tư sản xuất sản phẩm thuộc Danh mục sản phẩm công nghệ cao được khuyến khích phát triển",
  "language": "vi",
  "status": "extracted_pending_review",
  "source": {
    "publisher": "Cổng Dịch vụ công Quốc gia",
    "source_url": "https://dichvucong.gov.vn/thu-tuc-hanh-chinh/019d2bf9-ab35-74bd-9458-f64db6c73bdb",
    "source_file": "chi-tiet-thu-tuc-2.002794.pdf",
    "source_path": "procedures/viec-lam/2.002794/chi-tiet-thu-tuc-2.002794.pdf",
    "page_count": 3,
    "extracted_at": "2026-07-18T05:02:29.398038+00:00",
    "extraction_method": "official_api_plus_pypdf_text_layer",
    "source_sha256": "c53296f5cbcdada052931ba5a2dcb3fb5001f74a13157169c2d722e30a974404"
  },
  "governance": {
    "review_status": "pending",
    "reviewed_at": null,
    "reviewer": null,
    "freshness_days": 30
  },
  "decision_number": "3110/QĐ-BKHCN",
  "implementation_level": "Cấp tỉnh",
  "procedure_type": "NOT_ASSIGNED_REGULATION",
  "sector": "Hoạt động khoa học và công nghệ",
  "target_users": [
    "Tổ chức (không bao gồm doanh nghiệp, HTX)",
    "Doanh nghiệp có vốn đầu tư nước ngoài",
    "Doanh nghiệp",
    "Tổ chức nước ngoài",
    "Hợp tác xã"
  ],
  "agency": {
    "competent_agency": "",
    "executing_agency": "Ủy ban nhân dân cấp tỉnh"
  },
  "steps": [
    {
      "order": 1,
      "title": "Bước 1",
      "description": "- Doanh nghiệp nộp hồ sơ đề nghị cấp Giấy chứng nhận doanh nghiệp thành lập mới từ dự án đầu tư sản xuất sản phẩm công nghệ cao cho Ủy ban nhân dân cấp tỉnh nơi doanh nghiệp đặt trụ sở chính thực hiện.\n- Ủy ban nhân dân cấp tỉnh tổ chức tiếp nhận, thẩm định hồ sơ.",
      "example": null,
      "source_page": 1
    }
  ],
  "documents": {
    "forms": [],
    "normally_required": [],
    "conditional": [
      {
        "name": "Bản thuyết minh doanh nghiệp đáp ứng các tiêu chí dự án đầu tư sản xuất sản phẩm công nghệ cao theo Biểu B2-TMDNTLM ban hành tại Phụ lục kèm theo Thông tư số 08/2025/TT-BKHCN ngày 21 tháng 6 năm 2025",
        "quantity": "1 bản chính",
        "attachment": null,
        "source_page": 2
      },
      {
        "name": "Đơn đề nghị cấp Giấy chứng nhận của doanh nghiệp thành lập mới theo Biểu B1-DNTLM  ban hành tại Phụ lục kèm theo Thông tư số 08/2025/TT-BKHCN ngày 21 tháng 6 năm 2025;",
        "quantity": "1 bản chính",
        "attachment": null,
        "source_page": 2
      }
    ]
  },
  "submission_methods": [
    {
      "code": "ONLINE",
      "label": "Trực tuyến",
      "processing_time": "35 ngày làm việc",
      "fee": "0",
      "description": "",
      "source_page": 2
    },
    {
      "code": "POSTAL",
      "label": "Qua dịch vụ bưu chính",
      "processing_time": "35 ngày làm việc",
      "fee": "0",
      "description": "",
      "source_page": null
    },
    {
      "code": "DIRECT",
      "label": "Trực tiếp",
      "processing_time": "35 ngày làm việc",
      "fee": "0",
      "description": "",
      "source_page": 2
    }
  ],
  "fees": {
    "summary": "0",
    "status": "free",
    "currency": "VND",
    "items": [
      {
        "submission_method_code": "ONLINE",
        "submission_method": "Trực tuyến",
        "amount_text": "0",
        "is_free": true,
        "source_page": 2
      },
      {
        "submission_method_code": "POSTAL",
        "submission_method": "Qua dịch vụ bưu chính",
        "amount_text": "0",
        "is_free": true,
        "source_page": null
      },
      {
        "submission_method_code": "DIRECT",
        "submission_method": "Trực tiếp",
        "amount_text": "0",
        "is_free": true,
        "source_page": 2
      }
    ]
  },
  "legal_bases": [
    {
      "title": "Thông tư quy định về việc phân cấp trong thực hiện thủ tục chứng nhận doanh nghiệp thành lập mới từ dự án đầu tư sản xuất sản phẩm công nghệ cao và chứng nhận cơ sở ươm tạo công nghệ cao, ươm tạo doanh nghiệp công nghệ cao",
      "document_number": "08/2025/TT-BKHCN",
      "source_page": 2
    },
    {
      "title": "Luật Công nghệ cao",
      "document_number": "21/2008/QH12",
      "source_page": 2
    },
    {
      "title": "Quyết định số 38/2020/QĐ-TTg ban hành Danh mục công nghệ cao được ưu tiên đầu tư phát triển và Danh mục sản phẩm công nghệ cao được khuyến khích phát triển",
      "document_number": "38/2020/QĐ-TTg",
      "source_page": 3
    },
    {
      "title": "Thông tư 33/2011/TT-BKHCN-Hướng dẫn về thẩm quyền, trình tự, thủ tục chứng nhận doanh nghiệp thành lập mới từ dự án đầu tư sản xuất sản phẩm thuộc Danh mục sản phẩm công nghệ cao được khuyến khích phát triển",
      "document_number": "33/2011/TT-BKHCN",
      "source_page": 1
    }
  ],
  "conditions": "",
  "results": [
    {
      "title": "Giấy chứng nhận doanh nghiệp thành lập mới từ dự án đầu tư sản xuất sản phẩm công nghệ cao. Trường hợp từ chối cấp giấy chứng nhận thì phải thông báo lý do bằng văn bản cho doanh nghiệp",
      "code": "KQ.G06.000592",
      "source_page": 3
    }
  ],
  "raw_sections": {
    "TRÌNH TỰ THỰC HIỆN": "- Doanh nghiệp nộp hồ sơ đề nghị cấp Giấy chứng nhận doanh nghiệp thành lập mới từ dự án đầu tư sản xuất sản phẩm công nghệ cao cho Ủy ban nhân dân cấp tỉnh nơi doanh nghiệp đặt trụ sở chính thực hiện.\n- Ủy ban nhân dân cấp tỉnh tổ chức tiếp nhận, thẩm định hồ sơ.",
    "THÀNH PHẦN HỒ SƠ": "Bản thuyết minh doanh nghiệp đáp ứng các tiêu chí dự án đầu tư sản xuất sản phẩm công nghệ cao theo Biểu B2-TMDNTLM ban hành tại Phụ lục kèm theo Thông tư số 08/2025/TT-BKHCN ngày 21 tháng 6 năm 2025\nĐơn đề nghị cấp Giấy chứng nhận của doanh nghiệp thành lập mới theo Biểu B1-DNTLM  ban hành tại Phụ lục kèm theo Thông tư số 08/2025/TT-BKHCN ngày 21 tháng 6 năm 2025;",
    "CÁCH THỨC THỰC HIỆN": "Trực tuyến: 35 ngày làm việc\nQua dịch vụ bưu chính: 35 ngày làm việc\nTrực tiếp: 35 ngày làm việc",
    "CĂN CỨ PHÁP LÝ": "Thông tư quy định về việc phân cấp trong thực hiện thủ tục chứng nhận doanh nghiệp thành lập mới từ dự án đầu tư sản xuất sản phẩm công nghệ cao và chứng nhận cơ sở ươm tạo công nghệ cao, ươm tạo doanh nghiệp công nghệ cao - 08/2025/TT-BKHCN\nLuật Công nghệ cao - 21/2008/QH12\nQuyết định số 38/2020/QĐ-TTg ban hành Danh mục công nghệ cao được ưu tiên đầu tư phát triển và Danh mục sản phẩm công nghệ cao được khuyến khích phát triển - 38/2020/QĐ-TTg\nThông tư 33/2011/TT-BKHCN-Hướng dẫn về thẩm quyền, trình tự, thủ tục chứng nhận doanh nghiệp thành lập mới từ dự án đầu tư sản xuất sản phẩm thuộc Danh mục sản phẩm công nghệ cao được khuyến khích phát triển - 33/2011/TT-BKHCN",
    "CƠ QUAN THỰC HIỆN": "Ủy ban nhân dân cấp tỉnh",
    "YÊU CẦU, ĐIỀU KIỆN THỰC HIỆN": "",
    "KẾT QUẢ XỬ LÝ": "Giấy chứng nhận doanh nghiệp thành lập mới từ dự án đầu tư sản xuất sản phẩm công nghệ cao. Trường hợp từ chối cấp giấy chứng nhận thì phải thông báo lý do bằng văn bản cho doanh nghiệp - KQ.G06.000592",
    "TỪ KHÓA": "",
    "MÔ TẢ": ""
  },
  "classification": {
    "sector": {
      "name": "Hoạt động khoa học và công nghệ",
      "slug": "hoat-ong-khoa-hoc-va-cong-nghe"
    },
    "implementation_levels": [
      {
        "name": "Cấp tỉnh",
        "slug": "cap-tinh"
      }
    ],
    "target_users": [
      {
        "name": "Tổ chức (không bao gồm doanh nghiệp, HTX)",
        "slug": "to-chuc-khong-bao-gom-doanh-nghiep-htx"
      },
      {
        "name": "Doanh nghiệp có vốn đầu tư nước ngoài",
        "slug": "doanh-nghiep-co-von-au-tu-nuoc-ngoai"
      },
      {
        "name": "Doanh nghiệp",
        "slug": "doanh-nghiep"
      },
      {
        "name": "Tổ chức nước ngoài",
        "slug": "to-chuc-nuoc-ngoai"
      },
      {
        "name": "Hợp tác xã",
        "slug": "hop-tac-xa"
      }
    ],
    "agencies": [
      {
        "name": "Ủy ban nhân dân cấp tỉnh",
        "slug": "uy-ban-nhan-dan-cap-tinh"
      }
    ],
    "administrative_scope": "not_specified"
  }
}
